CHANGES.rst
CONTRIBUTORS.rst
MANIFEST.in
README.rst
setup.py
docs/LICENSE.GPL
docs/LICENSE.txt
src/interlegis/__init__.py
src/interlegis.portalmodelo.pl.egg-info/PKG-INFO
src/interlegis.portalmodelo.pl.egg-info/SOURCES.txt
src/interlegis.portalmodelo.pl.egg-info/dependency_links.txt
src/interlegis.portalmodelo.pl.egg-info/entry_points.txt
src/interlegis.portalmodelo.pl.egg-info/namespace_packages.txt
src/interlegis.portalmodelo.pl.egg-info/not-zip-safe
src/interlegis.portalmodelo.pl.egg-info/requires.txt
src/interlegis.portalmodelo.pl.egg-info/top_level.txt
src/interlegis/portalmodelo/__init__.py
src/interlegis/portalmodelo/pl/__init__.py
src/interlegis/portalmodelo/pl/config.py
src/interlegis/portalmodelo/pl/configure.zcml
src/interlegis/portalmodelo/pl/interfaces.py
src/interlegis/portalmodelo/pl/profiles.zcml
src/interlegis/portalmodelo/pl/setuphandlers.py
src/interlegis/portalmodelo/pl/testing.py
src/interlegis/portalmodelo/pl/utils.py
src/interlegis/portalmodelo/pl/validators.py
src/interlegis/portalmodelo/pl/Extensions/Install.py
src/interlegis/portalmodelo/pl/Extensions/__init__.py
src/interlegis/portalmodelo/pl/browser/__init__.py
src/interlegis/portalmodelo/pl/browser/configure.zcml
src/interlegis/portalmodelo/pl/browser/json_api.py
src/interlegis/portalmodelo/pl/browser/legislature.py
src/interlegis/portalmodelo/pl/browser/parliamentarian.py
src/interlegis/portalmodelo/pl/browser/session.py
src/interlegis/portalmodelo/pl/browser/templates/board_members.pt
src/interlegis/portalmodelo/pl/browser/templates/legislative_board.pt
src/interlegis/portalmodelo/pl/browser/templates/legislature_members.pt
src/interlegis/portalmodelo/pl/browser/templates/legislature_view.pt
src/interlegis/portalmodelo/pl/browser/templates/parliamentarian_view.pt
src/interlegis/portalmodelo/pl/browser/templates/parliamentarians.pt
src/interlegis/portalmodelo/pl/browser/templates/session_view.pt
src/interlegis/portalmodelo/pl/content/__init__.py
src/interlegis/portalmodelo/pl/content/legislature.py
src/interlegis/portalmodelo/pl/content/parliamentarian.py
src/interlegis/portalmodelo/pl/content/session.py
src/interlegis/portalmodelo/pl/locales/interlegis.portalmodelo.pl.pot
src/interlegis/portalmodelo/pl/locales/manual.pot
src/interlegis/portalmodelo/pl/locales/plone.pot
src/interlegis/portalmodelo/pl/locales/pt_BR/LC_MESSAGES/interlegis.portalmodelo.pl.po
